omop_lite/__init__.py
omop_lite/cli.py
omop_lite/settings.py
omop_lite/db/__init__.py
omop_lite/db/base.py
omop_lite/db/postgres.py
omop_lite/db/sqlserver.py
omop_lite/scripts/fts.sql
omop_lite/scripts/mssql/constraints.sql
omop_lite/scripts/mssql/ddl.sql
omop_lite/scripts/mssql/indices.sql
omop_lite/scripts/mssql/primary_keys.sql
omop_lite/scripts/pg/constraints.sql
omop_lite/scripts/pg/ddl.sql
omop_lite/scripts/pg/fts_index.sql
omop_lite/scripts/pg/indices.sql
omop_lite/scripts/pg/primary_keys.sql
omop_lite/synthetic/100/CDM_SOURCE.csv
omop_lite/synthetic/100/CONCEPT.csv
omop_lite/synthetic/100/CONCEPT_ANCESTOR.csv
omop_lite/synthetic/100/CONCEPT_CLASS.csv
omop_lite/synthetic/100/CONCEPT_RELATIONSHIP.csv
omop_lite/synthetic/100/CONCEPT_SYNONYM.csv
omop_lite/synthetic/100/CONDITION_OCCURRENCE.csv
omop_lite/synthetic/100/DOMAIN.csv
omop_lite/synthetic/100/DRUG_STRENGTH.csv
omop_lite/synthetic/100/MEASUREMENT.csv
omop_lite/synthetic/100/OBSERVATION.csv
omop_lite/synthetic/100/PERSON.csv
omop_lite/synthetic/100/RELATIONSHIP.csv
omop_lite/synthetic/100/VOCABULARY.csv
omop_lite/synthetic/1000/CONCEPT.csv
omop_lite/synthetic/1000/CONDITION_ERA.csv
omop_lite/synthetic/1000/CONDITION_OCCURRENCE.csv
omop_lite/synthetic/1000/DRUG_ERA.csv
omop_lite/synthetic/1000/DRUG_EXPOSURE.csv
omop_lite/synthetic/1000/MEASUREMENT.csv
omop_lite/synthetic/1000/OBSERVATION.csv
omop_lite/synthetic/1000/OBSERVATION_PERIOD.csv
omop_lite/synthetic/1000/PERSON.csv
omop_lite/synthetic/1000/PROCEDURE_OCCURRENCE.csv
omop_lite/synthetic/1000/VISIT_OCCURRENCE.csv
omop_lite-0.1.1.dist-info/METADATA
omop_lite-0.1.1.dist-info/WHEEL
omop_lite-0.1.1.dist-info/entry_points.txt
omop_lite-0.1.1.dist-info/licenses/LICENSE
omop_lite-0.1.1.dist-info/RECORD
