Metadata-Version: 2.4
Name: omop-lite
Version: 0.1.1
Summary: Get an OMOP CDM database running quickly.
License-File: LICENSE
Requires-Python: >=3.13
Requires-Dist: psycopg2-binary>=2.9.10
Requires-Dist: pydantic-settings>=2.8.1
Requires-Dist: pyodbc>=5.2.0
Requires-Dist: sqlalchemy>=2.0.39
Requires-Dist: typer>=0.16.0
